kufar/__init__.py
kufar/_instance.py
kufar/base/__init__.py
kufar/base/consts.py
kufar/base/service.py
kufar/packages/__init__.py
kufar/packages/account/__init__.py
kufar/packages/account/consts.py
kufar/packages/account/instance.py
kufar/packages/account/schemas.py
kufar/packages/ads/__init__.py
kufar/packages/ads/consts.py
kufar/packages/ads/instance.py
kufar/packages/ads/schemas.py
kufar/packages/auth/__init__.py
kufar/packages/auth/consts.py
kufar/packages/auth/instance.py
kufar/packages/auth/schemas.py
kufar/packages/categories/__init__.py
kufar/packages/categories/consts.py
kufar/packages/categories/instance.py
kufar/packages/categories/schemas.py
kufar/packages/favorites/__init__.py
kufar/packages/favorites/consts.py
kufar/packages/filters/__init__.py
kufar/packages/filters/consts.py
kufar/packages/filters/instance.py
kufar/packages/filters/schemas.py
kufar/packages/messaging/__init__.py
kufar/packages/messaging/consts.py
kufar/packages/messaging/instance.py
kufar/packages/messaging/schemas.py
kufar/packages/saved/__init__.py
kufar/packages/saved/consts.py
kufar/packages/saved/instance.py
kufar/packages/saved/schemas.py
kufar/packages/user_ads/__init__.py
kufar/packages/user_ads/consts.py
kufar/packages/user_ads/instance.py
kufar/packages/user_ads/schemas.py
kufar/schemas.py
kufar/utils/__init__.py
kufar/utils/auth.py
kufar/utils/requester.py
kufar/utils/signature_decoder.py
kufar/utils/state.py
kufar-0.1.3.dist-info/METADATA
kufar-0.1.3.dist-info/WHEEL
kufar-0.1.3.dist-info/RECORD
