Metadata-Version: 2.1
Name: kufar
Version: 0.1.3
Summary: 
Keywords: kufar,kufar-api,kufar_api
Author: Kiel Ed
Author-email: kieledssh@gmail.com
Requires-Python: >=3.10,<4.0
Classifier: Intended Audience :: Developers
Classifier: License :: OSI Approved :: MIT License
Classifier: Programming Language :: Python
Classifier: Programming Language :: Python :: 3
Classifier: Programming Language :: Python :: 3.10
Classifier: Programming Language :: Python :: 3.11
Classifier: Programming Language :: Python :: Implementation :: PyPy
Classifier: Topic :: Software Development :: Libraries :: Python Modules
Requires-Dist: aiofiles (>=23.1.0,<24.0.0)
Requires-Dist: aiohttp (>=3.8.5,<4.0.0)
Requires-Dist: pydantic (>=2.0.3,<3.0.0)
